Metadata-Version: 1.0
Name: markymarkov
Version: 0.1.0
Summary: Utility function for markovify
Home-page: https://github.com/MineRobber9000/markymarkov
Author: Robert Miles
Author-email: khuxkm+pip@tilde.team
License: UNKNOWN
Keywords: markov
Platform: UNKNOWN
